verysimplendle_augusto/__init__.py
verysimplendle_augusto/add.py
verysimplendle_augusto/subtract.py
verysimplendle_augusto/extra/__init__.py
verysimplendle_augusto/extra/divide.py
verysimplendle_augusto/extra/multiply.py
verysimplendle_augusto-0.0.1.dist-info/METADATA
verysimplendle_augusto-0.0.1.dist-info/WHEEL
verysimplendle_augusto-0.0.1.dist-info/top_level.txt
verysimplendle_augusto-0.0.1.dist-info/RECORD
